setup.py
logsnada/__init__.py
logsnada/config.py
logsnada/handler.py
logsnada.egg-info/PKG-INFO
logsnada.egg-info/SOURCES.txt
logsnada.egg-info/dependency_links.txt
logsnada.egg-info/top_level.txt