Metadata-Version: 1.1
Name: logsnada
Version: 0.2.7.4
Summary: Mostly about pattern-based definition of logger names
Home-page: https://github.com/RiverMeadow/logsnada
Author: Volodymyr Vitvitskyi
Author-email: vvitvitskiy@rivermeadow.com
License: UNKNOWN
Platform: UNKNOWN
Classifier: Programming Language :: Python
Classifier: Operating System :: OS Independent
Classifier: Environment :: Other Environment
Classifier: Intended Audience :: Developers
Classifier: Topic :: Software Development :: Libraries :: Python Modules
Classifier: Topic :: System :: Logging
